Obstacles/__init__.py
Obstacles/main.py
obstacles-2.0.dist-info/METADATA
obstacles-2.0.dist-info/WHEEL
obstacles-2.0.dist-info/entry_points.txt
obstacles-2.0.dist-info/top_level.txt
obstacles-2.0.dist-info/RECORD
