Metadata-Version: 2.1
Name: obstacles
Version: 2.0
Summary: This is a simple arcade-style game where you have to miss the obstacles
